tests/__init__.py
tests/test_api_key_manager.py
tests/test_config_loader.py
tests/test_logger_config.py
pycoretoolkit-0.1.0.dist-info/LICENSE
pycoretoolkit-0.1.0.dist-info/METADATA
pycoretoolkit-0.1.0.dist-info/WHEEL
pycoretoolkit-0.1.0.dist-info/entry_points.txt
pycoretoolkit-0.1.0.dist-info/top_level.txt
pycoretoolkit-0.1.0.dist-info/RECORD
