Metadata-Version: 2.1
Name: pycoretoolkit
Version: 0.1.0
Classifier: Programming Language :: Python :: 3
Classifier: License :: OSI Approved :: MIT License
Classifier: Operating System :: OS Independent
Requires-Python: >=3.6
License-File: LICENSE
Requires-Dist: setuptools
Requires-Dist: pyyaml
Requires-Dist: keyring
Requires-Dist: pytest
Requires-Dist: pre-commit
Requires-Dist: black
Requires-Dist: pykeepass
Requires-Dist: toml
Requires-Dist: wheel
Provides-Extra: dev
Requires-Dist: pytest ; extra == 'dev'
Requires-Dist: pytest-cov ; extra == 'dev'
Requires-Dist: bandit ; extra == 'dev'
Requires-Dist: safety ; extra == 'dev'
Requires-Dist: ruff ; extra == 'dev'
Requires-Dist: black ; extra == 'dev'
